lynk/__init__.py
lynk/exceptions.py
lynk/lock.py
lynk/refresh.py
lynk/session.py
lynk/techniques.py
lynk/utils.py
lynk/backends/__init__.py
lynk/backends/base.py
lynk/backends/dynamodb.py
lynk-0.3.1.data/scripts/lynk
lynk-0.3.1.dist-info/METADATA
lynk-0.3.1.dist-info/RECORD
lynk-0.3.1.dist-info/WHEEL
lynk-0.3.1.dist-info/top_level.txt
